<?xml version="1.0" encoding="UTF-8"?>
<!DOCTYPE beans PUBLIC "-//SPRING//DTD BEAN//EN" "http://www.springframework.org/dtd/spring-beans.dtd">

<!--
  - Application context definition for "springapp" DispatcherServlet.
  -->
<beans>
  	<bean id="dataSource" class="org.apache.commons.dbcp.BasicDataSource" destroy-method="close">
  		<property name="driverClassName">
  			<value>com.mysql.jdbc.Driver</value>
  		</property>
  		<property name="url">
  			<value>jdbc:mysql://127.0.0.1:3306/chaturanga</value>
  		</property>
  		<property name="username">
  			<value>root</value>
  		</property>
  		<property name="password">
			<value></value>
  		</property>
  	</bean>
  	
  	<bean id="sessionFactory" class="org.springframework.orm.hibernate3.LocalSessionFactoryBean">
  		<property name="dataSource">
  			<ref local="dataSource"/>
  		</property>
  		<property name="mappingResources">
  			<list>
  				<value>BaseDomainObject.hbm.xml</value>
  				<value>Game.hbm.xml</value>
  				<value>Move.hbm.xml</value>
  				<value>Player.hbm.xml</value>
  				<value>Unit.hbm.xml</value>
  			</list>
  		</property>
  		<property name="hibernateProperties">
  			<props>
  				<prop key="hibernate.dialect">org.hibernate.dialect.MySQL5Dialect</prop>
  				<prop key="hibernate.max_fetch_depth">3</prop>
  			</props>
  		</property>
  	</bean>

    <bean id="chaturangaController" class="org.seansawyer.chaturanga.controller.ChaturangaController">
    	<property name="playerService">
            <ref bean="playerService"/>
        </property>
    </bean>
    
    <bean id="playerService" class="org.seansawyer.chaturanga.model.service.PlayerServiceImpl">
        <property name="players">
            <list>
                <ref bean="player1"/>
                <ref bean="player2"/>
                <ref bean="player3"/>
            </list>
        </property>
    </bean>
    
    <bean id="player1" class="org.seansawyer.chaturanga.model.dom.Player">
        <property name="username"><value>d00dasaurus</value></property>
        <property name="fullName"><value>Jack Johnson</value></property>
    </bean>
    
    <bean id="player2" class="org.seansawyer.chaturanga.model.dom.Player">
        <property name="username"><value>hypnotiq</value></property>
        <property name="fullName"><value>Herman Sellers</value></property>
    </bean>
    
    <bean id="player3" class="org.seansawyer.chaturanga.model.dom.Player">
        <property name="username"><value>dookiebrain14</value></property>
        <property name="fullName"><value>Seth Grumbles</value></property>
    </bean>

    <bean id="messageSource" class="org.springframework.context.support.ResourceBundleMessageSource">
        <property name="basename"><value>application</value></property>
    </bean>

    <bean id="urlMapping" class="org.springframework.web.servlet.handler.SimpleUrlHandlerMapping">
        <property name="mappings">
            <props>
                <prop key="/hello.html">chaturangaController</prop>
            </props>
        </property>
    </bean>

    <bean id="viewResolver" class="org.springframework.web.servlet.view.InternalResourceViewResolver">
        <property name="viewClass"><value>org.springframework.web.servlet.view.JstlView</value></property>
        <property name="prefix"><value>/WEB-INF/jsp/</value></property>
        <property name="suffix"><value>.jsp</value></property>
    </bean>
</beans>